medcam/__init__.py
medcam/medcam.py
medcam/medcam_inject.py
medcam/medcam_utils.py
medcam/backends/__init__.py
medcam/backends/base.py
medcam/backends/grad_cam.py
medcam/backends/grad_cam_pp.py
medcam/backends/guided_backpropagation.py
medcam/backends/guided_grad_cam.py
medcam/evaluation/__init__.py
medcam/evaluation/evaluation_utils.py
medcam/evaluation/evaluator.py
tests/__init__.py
tests/test_classification/__init__.py
tests/test_classification/resnet_test.py
tests/test_segmentation/__init__.py
tests/test_segmentation/unet_seg_dataset.py
tests/test_segmentation/unet_seg_test.py
medcam-0.1.19.dist-info/LICENSE
medcam-0.1.19.dist-info/METADATA
medcam-0.1.19.dist-info/WHEEL
medcam-0.1.19.dist-info/top_level.txt
medcam-0.1.19.dist-info/RECORD
